typedb_graph_utils/__init__.py
typedb_graph_utils/converter.py
typedb_graph_utils/data_constraint.py
typedb_graph_utils/matplotlib_visualizer.py
typedb_graph_utils/networkx_builder.py
typedb_graph_utils-3.7.0.dist-info/licenses/LICENSE
typedb_graph_utils-3.7.0.dist-info/METADATA
typedb_graph_utils-3.7.0.dist-info/WHEEL
typedb_graph_utils-3.7.0.dist-info/top_level.txt
typedb_graph_utils-3.7.0.dist-info/RECORD
