Metadata-Version: 2.4
Name: typedb-graph-utils
Version: 3.7.0
Summary: TypeDB graph utils for python
Author-email: Krishnan Govindraj <krishnan@typedb.com>
License:                                  Apache License
Project-URL: Repository, https://github.com/typedb-osi/typedb-graph-utils
Project-URL: Release notes, https://github.com/typedb-osi/typedb-graph-utils/blob/master/RELEASE_NOTES.md
Project-URL: TypeDB server, https://github.com/typedb/typedb
Project-URL: TypeDB, https://typedb.com/
Classifier: Development Status :: 4 - Beta
Classifier: Environment :: Console
Classifier: Framework :: IPython
Classifier: License :: OSI Approved :: Apache Software License
Classifier: Natural Language :: English
Classifier: Programming Language :: Python :: 3
Classifier: Topic :: Database
Requires-Python: >=3.9
License-File: LICENSE
Requires-Dist: typedb-driver~=3.7.0
Requires-Dist: networkx~=3.2.1
Requires-Dist: matplotlib~=3.9.4
Provides-Extra: dev
Requires-Dist: pytest~=8.4.2; extra == "dev"
Requires-Dist: build~=1.3.0; extra == "dev"
Requires-Dist: jupyter~=1.1.1; extra == "dev"
Dynamic: license-file
